tdd/__init__.py
tdd/aliases.py
tdd/filters.py
tdd/healpix.py
tdd/healpixTiles.py
tdd/io.py
tdd/lightcurve.py
tdd/photometry.py
tdd/tessellations.py
tdd/test_healpix.py
tdd/version.py
tdd/visualization.py
tdd/example_data/plasticc_train_meta.csv
tdd/example_data/plasticc_train_phot.csv
tdd-0.0.4.dist-info/METADATA
tdd-0.0.4.dist-info/WHEEL
tdd-0.0.4.dist-info/pbr.json
tdd-0.0.4.dist-info/top_level.txt
tdd-0.0.4.dist-info/RECORD
