Metadata-Version: 2.1
Name: tdd
Version: 0.0.4
Summary: repo for handling Time Domain Astronomy Data
Home-page: UNKNOWN
Author: UNKNOWN
Author-email: UNKNOWN
License: UNKNOWN
Platform: UNKNOWN
